deepedgeai
