Metadata-Version: 1.0
Name: deepedgeai
Version: 0.0.1
Summary: A DeepEdge.ai Projects
Home-page: UNKNOWN
Author: UNKNOWN
Author-email: UNKNOWN
License: UNKNOWN
Platform: UNKNOWN
